{
  "id": "c6ad7247-0bba-4bf5-a2a0-82065433c673",
  "prevId": "00000000-0000-0000-0000-000000000000",
  "version": "7",
  "dialect": "postgresql",
  "tables": {
    "public.bookmarks": {
      "name": "bookmarks",
      "schema": "",
      "columns": {
        "id": {
          "name": "id",
          "type": "varchar",
          "primaryKey": true,
          "notNull": true,
          "default": "gen_random_uuid()"
        },
        "user_id": {
          "name": "user_id",
          "type": "varchar",
          "primaryKey": false,
          "notNull": true
        },
        "entity_type": {
          "name": "entity_type",
          "type": "text",
          "primaryKey": false,
          "notNull": true
        },
        "entity_id": {
          "name": "entity_id",
          "type": "varchar",
          "primaryKey": false,
          "notNull": true
        },
        "created_at": {
          "name": "created_at",
          "type": "timestamp",
          "primaryKey": false,
          "notNull": true,
          "default": "now()"
        }
      },
      "indexes": {},
      "foreignKeys": {
        "bookmarks_user_id_users_id_fk": {
          "name": "bookmarks_user_id_users_id_fk",
          "tableFrom": "bookmarks",
          "tableTo": "users",
          "columnsFrom": [
            "user_id"
          ],
          "columnsTo": [
            "id"
          ],
          "onDelete": "cascade",
          "onUpdate": "no action"
        }
      },
      "compositePrimaryKeys": {},
      "uniqueConstraints": {},
      "policies": {},
      "checkConstraints": {},
      "isRLSEnabled": false
    },
    "public.charge_plugin_configs": {
      "name": "charge_plugin_configs",
      "schema": "",
      "columns": {
        "id": {
          "name": "id",
          "type": "varchar",
          "primaryKey": true,
          "notNull": true,
          "default": "gen_random_uuid()"
        },
        "plugin_id": {
          "name": "plugin_id",
          "type": "text",
          "primaryKey": false,
          "notNull": true
        },
        "enabled": {
          "name": "enabled",
          "type": "boolean",
          "primaryKey": false,
          "notNull": true,
          "default": false
        },
        "scope": {
          "name": "scope",
          "type": "varchar",
          "primaryKey": false,
          "notNull": true
        },
        "employer_id": {
          "name": "employer_id",
          "type": "varchar",
          "primaryKey": false,
          "notNull": false
        },
        "settings": {
          "name": "settings",
          "type": "jsonb",
          "primaryKey": false,
          "notNull": false,
          "default": "'{}'"
        },
        "created_at": {
          "name": "created_at",
          "type": "timestamp",
          "primaryKey": false,
          "notNull": true,
          "default": "now()"
        },
        "updated_at": {
          "name": "updated_at",
          "type": "timestamp",
          "primaryKey": false,
          "notNull": true,
          "default": "now()"
        }
      },
      "indexes": {},
      "foreignKeys": {
        "charge_plugin_configs_employer_id_employers_id_fk": {
          "name": "charge_plugin_configs_employer_id_employers_id_fk",
          "tableFrom": "charge_plugin_configs",
          "tableTo": "employers",
          "columnsFrom": [
            "employer_id"
          ],
          "columnsTo": [
            "id"
          ],
          "onDelete": "cascade",
          "onUpdate": "no action"
        }
      },
      "compositePrimaryKeys": {},
      "uniqueConstraints": {
        "charge_plugin_configs_plugin_id_scope_employer_id_unique": {
          "name": "charge_plugin_configs_plugin_id_scope_employer_id_unique",
          "nullsNotDistinct": false,
          "columns": [
            "plugin_id",
            "scope",
            "employer_id"
          ]
        }
      },
      "policies": {},
      "checkConstraints": {},
      "isRLSEnabled": false
    },
    "public.comm": {
      "name": "comm",
      "schema": "",
      "columns": {
        "id": {
          "name": "id",
          "type": "varchar",
          "primaryKey": true,
          "notNull": true,
          "default": "gen_random_uuid()"
        },
        "medium": {
          "name": "medium",
          "type": "varchar",
          "primaryKey": false,
          "notNull": true
        },
        "contact_id": {
          "name": "contact_id",
          "type": "varchar",
          "primaryKey": false,
          "notNull": true
        },
        "status": {
          "name": "status",
          "type": "varchar",
          "primaryKey": false,
          "notNull": true
        },
        "sent": {
          "name": "sent",
          "type": "timestamp",
          "primaryKey": false,
          "notNull": false
        },
        "received": {
          "name": "received",
          "type": "timestamp",
          "primaryKey": false,
          "notNull": false
        },
        "data": {
          "name": "data",
          "type": "jsonb",
          "primaryKey": false,
          "notNull": false
        }
      },
      "indexes": {},
      "foreignKeys": {
        "comm_contact_id_contacts_id_fk": {
          "name": "comm_contact_id_contacts_id_fk",
          "tableFrom": "comm",
          "tableTo": "contacts",
          "columnsFrom": [
            "contact_id"
          ],
          "columnsTo": [
            "id"
          ],
          "onDelete": "cascade",
          "onUpdate": "no action"
        }
      },
      "compositePrimaryKeys": {},
      "uniqueConstraints": {},
      "policies": {},
      "checkConstraints": {},
      "isRLSEnabled": false
    },
    "public.comm_email": {
      "name": "comm_email",
      "schema": "",
      "columns": {
        "id": {
          "name": "id",
          "type": "varchar",
          "primaryKey": true,
          "notNull": true,
          "default": "gen_random_uuid()"
        },
        "comm_id": {
          "name": "comm_id",
          "type": "varchar",
          "primaryKey": false,
          "notNull": true
        },
        "to": {
          "name": "to",
          "type": "text",
          "primaryKey": false,
          "notNull": false
        },
        "to_name": {
          "name": "to_name",
          "type": "varchar",
          "primaryKey": false,
          "notNull": false
        },
        "from_address": {
          "name": "from_address",
          "type": "text",
          "primaryKey": false,
          "notNull": false
        },
        "from_name": {
          "name": "from_name",
          "type": "varchar",
          "primaryKey": false,
          "notNull": false
        },
        "reply_to": {
          "name": "reply_to",
          "type": "text",
          "primaryKey": false,
          "notNull": false
        },
        "subject": {
          "name": "subject",
          "type": "text",
          "primaryKey": false,
          "notNull": false
        },
        "body_text": {
          "name": "body_text",
          "type": "text",
          "primaryKey": false,
          "notNull": false
        },
        "body_html": {
          "name": "body_html",
          "type": "text",
          "primaryKey": false,
          "notNull": false
        },
        "data": {
          "name": "data",
          "type": "jsonb",
          "primaryKey": false,
          "notNull": false
        }
      },
      "indexes": {},
      "foreignKeys": {
        "comm_email_comm_id_comm_id_fk": {
          "name": "comm_email_comm_id_comm_id_fk",
          "tableFrom": "comm_email",
          "tableTo": "comm",
          "columnsFrom": [
            "comm_id"
          ],
          "columnsTo": [
            "id"
          ],
          "onDelete": "cascade",
          "onUpdate": "no action"
        }
      },
      "compositePrimaryKeys": {},
      "uniqueConstraints": {},
      "policies": {},
      "checkConstraints": {},
      "isRLSEnabled": false
    },
    "public.comm_email_optin": {
      "name": "comm_email_optin",
      "schema": "",
      "columns": {
        "id": {
          "name": "id",
          "type": "varchar",
          "primaryKey": true,
          "notNull": true,
          "default": "gen_random_uuid()"
        },
        "email": {
          "name": "email",
          "type": "text",
          "primaryKey": false,
          "notNull": true
        },
        "optin": {
          "name": "optin",
          "type": "boolean",
          "primaryKey": false,
          "notNull": true,
          "default": false
        },
        "optin_user": {
          "name": "optin_user",
          "type": "varchar",
          "primaryKey": false,
          "notNull": false
        },
        "optin_date": {
          "name": "optin_date",
          "type": "timestamp",
          "primaryKey": false,
          "notNull": false
        },
        "optin_ip": {
          "name": "optin_ip",
          "type": "varchar",
          "primaryKey": false,
          "notNull": false
        },
        "allowlist": {
          "name": "allowlist",
          "type": "boolean",
          "primaryKey": false,
          "notNull": true,
          "default": false
        },
        "public_token": {
          "name": "public_token",
          "type": "varchar",
          "primaryKey": false,
          "notNull": false
        },
        "email_valid": {
          "name": "email_valid",
          "type": "boolean",
          "primaryKey": false,
          "notNull": false
        },
        "validated_at": {
          "name": "validated_at",
          "type": "timestamp",
          "primaryKey": false,
          "notNull": false
        },
        "validation_response": {
          "name": "validation_response",
          "type": "jsonb",
          "primaryKey": false,
          "notNull": false
        }
      },
      "indexes": {},
      "foreignKeys": {
        "comm_email_optin_optin_user_users_id_fk": {
          "name": "comm_email_optin_optin_user_users_id_fk",
          "tableFrom": "comm_email_optin",
          "tableTo": "users",
          "columnsFrom": [
            "optin_user"
          ],
          "columnsTo": [
            "id"
          ],
          "onDelete": "set null",
          "onUpdate": "no action"
        }
      },
      "compositePrimaryKeys": {},
      "uniqueConstraints": {
        "comm_email_optin_email_unique": {
          "name": "comm_email_optin_email_unique",
          "nullsNotDistinct": false,
          "columns": [
            "email"
          ]
        },
        "comm_email_optin_public_token_unique": {
          "name": "comm_email_optin_public_token_unique",
          "nullsNotDistinct": false,
          "columns": [
            "public_token"
          ]
        }
      },
      "policies": {},
      "checkConstraints": {},
      "isRLSEnabled": false
    },
    "public.comm_postal": {
      "name": "comm_postal",
      "schema": "",
      "columns": {
        "id": {
          "name": "id",
          "type": "varchar",
          "primaryKey": true,
          "notNull": true,
          "default": "gen_random_uuid()"
        },
        "comm_id": {
          "name": "comm_id",
          "type": "varchar",
          "primaryKey": false,
          "notNull": true
        },
        "to_name": {
          "name": "to_name",
          "type": "varchar",
          "primaryKey": false,
          "notNull": false
        },
        "to_company": {
          "name": "to_company",
          "type": "varchar",
          "primaryKey": false,
          "notNull": false
        },
        "to_address_line1": {
          "name": "to_address_line1",
          "type": "text",
          "primaryKey": false,
          "notNull": true
        },
        "to_address_line2": {
          "name": "to_address_line2",
          "type": "text",
          "primaryKey": false,
          "notNull": false
        },
        "to_city": {
          "name": "to_city",
          "type": "text",
          "primaryKey": false,
          "notNull": true
        },
        "to_state": {
          "name": "to_state",
          "type": "text",
          "primaryKey": false,
          "notNull": true
        },
        "to_zip": {
          "name": "to_zip",
          "type": "text",
          "primaryKey": false,
          "notNull": true
        },
        "to_country": {
          "name": "to_country",
          "type": "text",
          "primaryKey": false,
          "notNull": true,
          "default": "'US'"
        },
        "from_name": {
          "name": "from_name",
          "type": "varchar",
          "primaryKey": false,
          "notNull": false
        },
        "from_company": {
          "name": "from_company",
          "type": "varchar",
          "primaryKey": false,
          "notNull": false
        },
        "from_address_line1": {
          "name": "from_address_line1",
          "type": "text",
          "primaryKey": false,
          "notNull": false
        },
        "from_address_line2": {
          "name": "from_address_line2",
          "type": "text",
          "primaryKey": false,
          "notNull": false
        },
        "from_city": {
          "name": "from_city",
          "type": "text",
          "primaryKey": false,
          "notNull": false
        },
        "from_state": {
          "name": "from_state",
          "type": "text",
          "primaryKey": false,
          "notNull": false
        },
        "from_zip": {
          "name": "from_zip",
          "type": "text",
          "primaryKey": false,
          "notNull": false
        },
        "from_country": {
          "name": "from_country",
          "type": "text",
          "primaryKey": false,
          "notNull": false,
          "default": "'US'"
        },
        "description": {
          "name": "description",
          "type": "text",
          "primaryKey": false,
          "notNull": false
        },
        "file_url": {
          "name": "file_url",
          "type": "text",
          "primaryKey": false,
          "notNull": false
        },
        "template_id": {
          "name": "template_id",
          "type": "varchar",
          "primaryKey": false,
          "notNull": false
        },
        "merge_variables": {
          "name": "merge_variables",
          "type": "jsonb",
          "primaryKey": false,
          "notNull": false
        },
        "color": {
          "name": "color",
          "type": "boolean",
          "primaryKey": false,
          "notNull": true,
          "default": false
        },
        "double_sided": {
          "name": "double_sided",
          "type": "boolean",
          "primaryKey": false,
          "notNull": true,
          "default": false
        },
        "mail_type": {
          "name": "mail_type",
          "type": "varchar",
          "primaryKey": false,
          "notNull": true,
          "default": "'usps_first_class'"
        },
        "extra_service": {
          "name": "extra_service",
          "type": "varchar",
          "primaryKey": false,
          "notNull": false
        },
        "lob_letter_id": {
          "name": "lob_letter_id",
          "type": "varchar",
          "primaryKey": false,
          "notNull": false
        },
        "lob_tracking_events": {
          "name": "lob_tracking_events",
          "type": "jsonb",
          "primaryKey": false,
          "notNull": false
        },
        "expected_delivery_date": {
          "name": "expected_delivery_date",
          "type": "timestamp",
          "primaryKey": false,
          "notNull": false
        },
        "data": {
          "name": "data",
          "type": "jsonb",
          "primaryKey": false,
          "notNull": false
        }
      },
      "indexes": {},
      "foreignKeys": {
        "comm_postal_comm_id_comm_id_fk": {
          "name": "comm_postal_comm_id_comm_id_fk",
          "tableFrom": "comm_postal",
          "tableTo": "comm",
          "columnsFrom": [
            "comm_id"
          ],
          "columnsTo": [
            "id"
          ],
          "onDelete": "cascade",
          "onUpdate": "no action"
        }
      },
      "compositePrimaryKeys": {},
      "uniqueConstraints": {},
      "policies": {},
      "checkConstraints": {},
      "isRLSEnabled": false
    },
    "public.comm_postal_optin": {
      "name": "comm_postal_optin",
      "schema": "",
      "columns": {
        "id": {
          "name": "id",
          "type": "varchar",
          "primaryKey": true,
          "notNull": true,
          "default": "gen_random_uuid()"
        },
        "canonical_address": {
          "name": "canonical_address",
          "type": "text",
          "primaryKey": false,
          "notNull": true
        },
        "address_line1": {
          "name": "address_line1",
          "type": "text",
          "primaryKey": false,
          "notNull": true
        },
        "address_line2": {
          "name": "address_line2",
          "type": "text",
          "primaryKey": false,
          "notNull": false
        },
        "city": {
          "name": "city",
          "type": "text",
          "primaryKey": false,
          "notNull": true
        },
        "state": {
          "name": "state",
          "type": "text",
          "primaryKey": false,
          "notNull": true
        },
        "zip": {
          "name": "zip",
          "type": "text",
          "primaryKey": false,
          "notNull": true
        },
        "country": {
          "name": "country",
          "type": "text",
          "primaryKey": false,
          "notNull": true,
          "default": "'US'"
        },
        "optin": {
          "name": "optin",
          "type": "boolean",
          "primaryKey": false,
          "notNull": true,
          "default": false
        },
        "optin_user": {
          "name": "optin_user",
          "type": "varchar",
          "primaryKey": false,
          "notNull": false
        },
        "optin_date": {
          "name": "optin_date",
          "type": "timestamp",
          "primaryKey": false,
          "notNull": false
        },
        "optin_ip": {
          "name": "optin_ip",
          "type": "varchar",
          "primaryKey": false,
          "notNull": false
        },
        "allowlist": {
          "name": "allowlist",
          "type": "boolean",
          "primaryKey": false,
          "notNull": true,
          "default": false
        },
        "public_token": {
          "name": "public_token",
          "type": "varchar",
          "primaryKey": false,
          "notNull": false
        },
        "deliverable": {
          "name": "deliverable",
          "type": "boolean",
          "primaryKey": false,
          "notNull": false
        },
        "deliverability_analysis": {
          "name": "deliverability_analysis",
          "type": "jsonb",
          "primaryKey": false,
          "notNull": false
        },
        "validated_at": {
          "name": "validated_at",
          "type": "timestamp",
          "primaryKey": false,
          "notNull": false
        },
        "validation_response": {
          "name": "validation_response",
          "type": "jsonb",
          "primaryKey": false,
          "notNull": false
        }
      },
      "indexes": {},
      "foreignKeys": {
        "comm_postal_optin_optin_user_users_id_fk": {
          "name": "comm_postal_optin_optin_user_users_id_fk",
          "tableFrom": "comm_postal_optin",
          "tableTo": "users",
          "columnsFrom": [
            "optin_user"
          ],
          "columnsTo": [
            "id"
          ],
          "onDelete": "set null",
          "onUpdate": "no action"
        }
      },
      "compositePrimaryKeys": {},
      "uniqueConstraints": {
        "comm_postal_optin_canonical_address_unique": {
          "name": "comm_postal_optin_canonical_address_unique",
          "nullsNotDistinct": false,
          "columns": [
            "canonical_address"
          ]
        },
        "comm_postal_optin_public_token_unique": {
          "name": "comm_postal_optin_public_token_unique",
          "nullsNotDistinct": false,
          "columns": [
            "public_token"
          ]
        }
      },
      "policies": {},
      "checkConstraints": {},
      "isRLSEnabled": false
    },
    "public.comm_sms": {
      "name": "comm_sms",
      "schema": "",
      "columns": {
        "id": {
          "name": "id",
          "type": "varchar",
          "primaryKey": true,
          "notNull": true,
          "default": "gen_random_uuid()"
        },
        "comm_id": {
          "name": "comm_id",
          "type": "varchar",
          "primaryKey": false,
          "notNull": true
        },
        "to": {
          "name": "to",
          "type": "varchar",
          "primaryKey": false,
          "notNull": false
        },
        "body": {
          "name": "body",
          "type": "text",
          "primaryKey": false,
          "notNull": false
        },
        "data": {
          "name": "data",
          "type": "jsonb",
          "primaryKey": false,
          "notNull": false
        }
      },
      "indexes": {},
      "foreignKeys": {
        "comm_sms_comm_id_comm_id_fk": {
          "name": "comm_sms_comm_id_comm_id_fk",
          "tableFrom": "comm_sms",
          "tableTo": "comm",
          "columnsFrom": [
            "comm_id"
          ],
          "columnsTo": [
            "id"
          ],
          "onDelete": "cascade",
          "onUpdate": "no action"
        }
      },
      "compositePrimaryKeys": {},
      "uniqueConstraints": {},
      "policies": {},
      "checkConstraints": {},
      "isRLSEnabled": false
    },
    "public.comm_sms_optin": {
      "name": "comm_sms_optin",
      "schema": "",
      "columns": {
        "id": {
          "name": "id",
          "type": "varchar",
          "primaryKey": true,
          "notNull": true,
          "default": "gen_random_uuid()"
        },
        "phone_number": {
          "name": "phone_number",
          "type": "text",
          "primaryKey": false,
          "notNull": true
        },
        "optin": {
          "name": "optin",
          "type": "boolean",
          "primaryKey": false,
          "notNull": true,
          "default": false
        },
        "optin_user": {
          "name": "optin_user",
          "type": "varchar",
          "primaryKey": false,
          "notNull": false
        },
        "optin_date": {
          "name": "optin_date",
          "type": "timestamp",
          "primaryKey": false,
          "notNull": false
        },
        "optin_ip": {
          "name": "optin_ip",
          "type": "varchar",
          "primaryKey": false,
          "notNull": false
        },
        "allowlist": {
          "name": "allowlist",
          "type": "boolean",
          "primaryKey": false,
          "notNull": true,
          "default": false
        },
        "public_token": {
          "name": "public_token",
          "type": "varchar",
          "primaryKey": false,
          "notNull": false
        },
        "sms_possible": {
          "name": "sms_possible",
          "type": "boolean",
          "primaryKey": false,
          "notNull": false
        },
        "voice_possible": {
          "name": "voice_possible",
          "type": "boolean",
          "primaryKey": false,
          "notNull": false
        },
        "validated_at": {
          "name": "validated_at",
          "type": "timestamp",
          "primaryKey": false,
          "notNull": false
        },
        "validation_response": {
          "name": "validation_response",
          "type": "jsonb",
          "primaryKey": false,
          "notNull": false
        }
      },
      "indexes": {},
      "foreignKeys": {
        "comm_sms_optin_optin_user_users_id_fk": {
          "name": "comm_sms_optin_optin_user_users_id_fk",
          "tableFrom": "comm_sms_optin",
          "tableTo": "users",
          "columnsFrom": [
            "optin_user"
          ],
          "columnsTo": [
            "id"
          ],
          "onDelete": "set null",
          "onUpdate": "no action"
        }
      },
      "compositePrimaryKeys": {},
      "uniqueConstraints": {
        "comm_sms_optin_phone_number_unique": {
          "name": "comm_sms_optin_phone_number_unique",
          "nullsNotDistinct": false,
          "columns": [
            "phone_number"
          ]
        },
        "comm_sms_optin_public_token_unique": {
          "name": "comm_sms_optin_public_token_unique",
          "nullsNotDistinct": false,
          "columns": [
            "public_token"
          ]
        }
      },
      "policies": {},
      "checkConstraints": {},
      "isRLSEnabled": false
    },
    "public.contact_postal": {
      "name": "contact_postal",
      "schema": "",
      "columns": {
        "id": {
          "name": "id",
          "type": "varchar",
          "primaryKey": true,
          "notNull": true,
          "default": "gen_random_uuid()"
        },
        "contact_id": {
          "name": "contact_id",
          "type": "varchar",
          "primaryKey": false,
          "notNull": true
        },
        "friendly_name": {
          "name": "friendly_name",
          "type": "text",
          "primaryKey": false,
          "notNull": false
        },
        "street": {
          "name": "street",
          "type": "text",
          "primaryKey": false,
          "notNull": true
        },
        "city": {
          "name": "city",
          "type": "text",
          "primaryKey": false,
          "notNull": true
        },
        "state": {
          "name": "state",
          "type": "text",
          "primaryKey": false,
          "notNull": true
        },
        "postal_code": {
          "name": "postal_code",
          "type": "text",
          "primaryKey": false,
          "notNull": true
        },
        "country": {
          "name": "country",
          "type": "text",
          "primaryKey": false,
          "notNull": true
        },
        "is_primary": {
          "name": "is_primary",
          "type": "boolean",
          "primaryKey": false,
          "notNull": true,
          "default": false
        },
        "is_active": {
          "name": "is_active",
          "type": "boolean",
          "primaryKey": false,
          "notNull": true,
          "default": true
        },
        "validation_response": {
          "name": "validation_response",
          "type": "jsonb",
          "primaryKey": false,
          "notNull": false
        },
        "latitude": {
          "name": "latitude",
          "type": "double precision",
          "primaryKey": false,
          "notNull": false
        },
        "longitude": {
          "name": "longitude",
          "type": "double precision",
          "primaryKey": false,
          "notNull": false
        },
        "accuracy": {
          "name": "accuracy",
          "type": "text",
          "primaryKey": false,
          "notNull": false
        },
        "created_at": {
          "name": "created_at",
          "type": "timestamp",
          "primaryKey": false,
          "notNull": true,
          "default": "now()"
        }
      },
      "indexes": {},
      "foreignKeys": {
        "contact_postal_contact_id_contacts_id_fk": {
          "name": "contact_postal_contact_id_contacts_id_fk",
          "tableFrom": "contact_postal",
          "tableTo": "contacts",
          "columnsFrom": [
            "contact_id"
          ],
          "columnsTo": [
            "id"
          ],
          "onDelete": "cascade",
          "onUpdate": "no action"
        }
      },
      "compositePrimaryKeys": {},
      "uniqueConstraints": {},
      "policies": {},
      "checkConstraints": {},
      "isRLSEnabled": false
    },
    "public.contacts": {
      "name": "contacts",
      "schema": "",
      "columns": {
        "id": {
          "name": "id",
          "type": "varchar",
          "primaryKey": true,
          "notNull": true,
          "default": "gen_random_uuid()"
        },
        "title": {
          "name": "title",
          "type": "text",
          "primaryKey": false,
          "notNull": false
        },
        "given": {
          "name": "given",
          "type": "text",
          "primaryKey": false,
          "notNull": false
        },
        "middle": {
          "name": "middle",
          "type": "text",
          "primaryKey": false,
          "notNull": false
        },
        "family": {
          "name": "family",
          "type": "text",
          "primaryKey": false,
          "notNull": false
        },
        "generational": {
          "name": "generational",
          "type": "text",
          "primaryKey": false,
          "notNull": false
        },
        "credentials": {
          "name": "credentials",
          "type": "text",
          "primaryKey": false,
          "notNull": false
        },
        "display_name": {
          "name": "display_name",
          "type": "text",
          "primaryKey": false,
          "notNull": true
        },
        "email": {
          "name": "email",
          "type": "text",
          "primaryKey": false,
          "notNull": false
        },
        "birth_date": {
          "name": "birth_date",
          "type": "date",
          "primaryKey": false,
          "notNull": false
        },
        "gender": {
          "name": "gender",
          "type": "varchar",
          "primaryKey": false,
          "notNull": false
        },
        "gender_nota": {
          "name": "gender_nota",
          "type": "text",
          "primaryKey": false,
          "notNull": false
        },
        "gender_calc": {
          "name": "gender_calc",
          "type": "text",
          "primaryKey": false,
          "notNull": false
        }
      },
      "indexes": {},
      "foreignKeys": {
        "contacts_gender_options_gender_id_fk": {
          "name": "contacts_gender_options_gender_id_fk",
          "tableFrom": "contacts",
          "tableTo": "options_gender",
          "columnsFrom": [
            "gender"
          ],
          "columnsTo": [
            "id"
          ],
          "onDelete": "set null",
          "onUpdate": "no action"
        }
      },
      "compositePrimaryKeys": {},
      "uniqueConstraints": {
        "contacts_email_unique": {
          "name": "contacts_email_unique",
          "nullsNotDistinct": false,
          "columns": [
            "email"
          ]
        }
      },
      "policies": {},
      "checkConstraints": {},
      "isRLSEnabled": false
    },
    "public.cron_job_runs": {
      "name": "cron_job_runs",
      "schema": "",
      "columns": {
        "id": {
          "name": "id",
          "type": "varchar",
          "primaryKey": true,
          "notNull": true,
          "default": "gen_random_uuid()"
        },
        "job_name": {
          "name": "job_name",
          "type": "text",
          "primaryKey": false,
          "notNull": true
        },
        "status": {
          "name": "status",
          "type": "varchar",
          "primaryKey": false,
          "notNull": true
        },
        "mode": {
          "name": "mode",
          "type": "varchar",
          "primaryKey": false,
          "notNull": true,
          "default": "'live'"
        },
        "output": {
          "name": "output",
          "type": "text",
          "primaryKey": false,
          "notNull": false
        },
        "error": {
          "name": "error",
          "type": "text",
          "primaryKey": false,
          "notNull": false
        },
        "started_at": {
          "name": "started_at",
          "type": "timestamp",
          "primaryKey": false,
          "notNull": true,
          "default": "now()"
        },
        "completed_at": {
          "name": "completed_at",
          "type": "timestamp",
          "primaryKey": false,
          "notNull": false
        },
        "triggered_by": {
          "name": "triggered_by",
          "type": "varchar",
          "primaryKey": false,
          "notNull": false
        }
      },
      "indexes": {},
      "foreignKeys": {
        "cron_job_runs_job_name_cron_jobs_name_fk": {
          "name": "cron_job_runs_job_name_cron_jobs_name_fk",
          "tableFrom": "cron_job_runs",
          "tableTo": "cron_jobs",
          "columnsFrom": [
            "job_name"
          ],
          "columnsTo": [
            "name"
          ],
          "onDelete": "cascade",
          "onUpdate": "no action"
        }
      },
      "compositePrimaryKeys": {},
      "uniqueConstraints": {},
      "policies": {},
      "checkConstraints": {},
      "isRLSEnabled": false
    },
    "public.cron_jobs": {
      "name": "cron_jobs",
      "schema": "",
      "columns": {
        "name": {
          "name": "name",
          "type": "text",
          "primaryKey": true,
          "notNull": true
        },
        "description": {
          "name": "description",
          "type": "text",
          "primaryKey": false,
          "notNull": false
        },
        "schedule": {
          "name": "schedule",
          "type": "text",
          "primaryKey": false,
          "notNull": true
        },
        "is_enabled": {
          "name": "is_enabled",
          "type": "boolean",
          "primaryKey": false,
          "notNull": true,
          "default": false
        },
        "created_at": {
          "name": "created_at",
          "type": "timestamp",
          "primaryKey": false,
          "notNull": true,
          "default": "now()"
        },
        "updated_at": {
          "name": "updated_at",
          "type": "timestamp",
          "primaryKey": false,
          "notNull": true,
          "default": "now()"
        }
      },
      "indexes": {},
      "foreignKeys": {},
      "compositePrimaryKeys": {},
      "uniqueConstraints": {},
      "policies": {},
      "checkConstraints": {},
      "isRLSEnabled": false
    },
    "public.employer_contacts": {
      "name": "employer_contacts",
      "schema": "",
      "columns": {
        "id": {
          "name": "id",
          "type": "varchar",
          "primaryKey": true,
          "notNull": true,
          "default": "gen_random_uuid()"
        },
        "employer_id": {
          "name": "employer_id",
          "type": "varchar",
          "primaryKey": false,
          "notNull": true
        },
        "contact_id": {
          "name": "contact_id",
          "type": "varchar",
          "primaryKey": false,
          "notNull": true
        },
        "contact_type_id": {
          "name": "contact_type_id",
          "type": "varchar",
          "primaryKey": false,
          "notNull": false
        }
      },
      "indexes": {},
      "foreignKeys": {
        "employer_contacts_employer_id_employers_id_fk": {
          "name": "employer_contacts_employer_id_employers_id_fk",
          "tableFrom": "employer_contacts",
          "tableTo": "employers",
          "columnsFrom": [
            "employer_id"
          ],
          "columnsTo": [
            "id"
          ],
          "onDelete": "cascade",
          "onUpdate": "no action"
        },
        "employer_contacts_contact_id_contacts_id_fk": {
          "name": "employer_contacts_contact_id_contacts_id_fk",
          "tableFrom": "employer_contacts",
          "tableTo": "contacts",
          "columnsFrom": [
            "contact_id"
          ],
          "columnsTo": [
            "id"
          ],
          "onDelete": "cascade",
          "onUpdate": "no action"
        },
        "employer_contacts_contact_type_id_options_employer_contact_type_id_fk": {
          "name": "employer_contacts_contact_type_id_options_employer_contact_type_id_fk",
          "tableFrom": "employer_contacts",
          "tableTo": "options_employer_contact_type",
          "columnsFrom": [
            "contact_type_id"
          ],
          "columnsTo": [
            "id"
          ],
          "onDelete": "set null",
          "onUpdate": "no action"
        }
      },
      "compositePrimaryKeys": {},
      "uniqueConstraints": {},
      "policies": {},
      "checkConstraints": {},
      "isRLSEnabled": false
    },
    "public.employers": {
      "name": "employers",
      "schema": "",
      "columns": {
        "id": {
          "name": "id",
          "type": "varchar",
          "primaryKey": true,
          "notNull": true,
          "default": "gen_random_uuid()"
        },
        "sirius_id": {
          "name": "sirius_id",
          "type": "serial",
          "primaryKey": false,
          "notNull": true
        },
        "name": {
          "name": "name",
          "type": "text",
          "primaryKey": false,
          "notNull": true
        },
        "is_active": {
          "name": "is_active",
          "type": "boolean",
          "primaryKey": false,
          "notNull": true,
          "default": true
        },
        "stripe_customer_id": {
          "name": "stripe_customer_id",
          "type": "text",
          "primaryKey": false,
          "notNull": false
        }
      },
      "indexes": {},
      "foreignKeys": {},
      "compositePrimaryKeys": {},
      "uniqueConstraints": {
        "employers_sirius_id_unique": {
          "name": "employers_sirius_id_unique",
          "nullsNotDistinct": false,
          "columns": [
            "sirius_id"
          ]
        }
      },
      "policies": {},
      "checkConstraints": {},
      "isRLSEnabled": false
    },
    "public.files": {
      "name": "files",
      "schema": "",
      "columns": {
        "id": {
          "name": "id",
          "type": "varchar",
          "primaryKey": true,
          "notNull": true,
          "default": "gen_random_uuid()"
        },
        "file_name": {
          "name": "file_name",
          "type": "varchar",
          "primaryKey": false,
          "notNull": true
        },
        "storage_path": {
          "name": "storage_path",
          "type": "varchar",
          "primaryKey": false,
          "notNull": true
        },
        "mime_type": {
          "name": "mime_type",
          "type": "varchar",
          "primaryKey": false,
          "notNull": false
        },
        "size": {
          "name": "size",
          "type": "integer",
          "primaryKey": false,
          "notNull": true
        },
        "uploaded_by": {
          "name": "uploaded_by",
          "type": "varchar",
          "primaryKey": false,
          "notNull": true
        },
        "uploaded_at": {
          "name": "uploaded_at",
          "type": "timestamp",
          "primaryKey": false,
          "notNull": true,
          "default": "now()"
        },
        "entity_type": {
          "name": "entity_type",
          "type": "varchar",
          "primaryKey": false,
          "notNull": false
        },
        "entity_id": {
          "name": "entity_id",
          "type": "varchar",
          "primaryKey": false,
          "notNull": false
        },
        "access_level": {
          "name": "access_level",
          "type": "varchar",
          "primaryKey": false,
          "notNull": true,
          "default": "'private'"
        },
        "metadata": {
          "name": "metadata",
          "type": "jsonb",
          "primaryKey": false,
          "notNull": false
        }
      },
      "indexes": {},
      "foreignKeys": {},
      "compositePrimaryKeys": {},
      "uniqueConstraints": {},
      "policies": {},
      "checkConstraints": {},
      "isRLSEnabled": false
    },
    "public.ledger": {
      "name": "ledger",
      "schema": "",
      "columns": {
        "id": {
          "name": "id",
          "type": "varchar",
          "primaryKey": true,
          "notNull": true,
          "default": "gen_random_uuid()"
        },
        "charge_plugin": {
          "name": "charge_plugin",
          "type": "varchar",
          "primaryKey": false,
          "notNull": true
        },
        "charge_plugin_key": {
          "name": "charge_plugin_key",
          "type": "varchar",
          "primaryKey": false,
          "notNull": true
        },
        "charge_plugin_config_id": {
          "name": "charge_plugin_config_id",
          "type": "varchar",
          "primaryKey": false,
          "notNull": false
        },
        "amount": {
          "name": "amount",
          "type": "numeric(10, 2)",
          "primaryKey": false,
          "notNull": true
        },
        "ea_id": {
          "name": "ea_id",
          "type": "varchar",
          "primaryKey": false,
          "notNull": true
        },
        "reference_type": {
          "name": "reference_type",
          "type": "varchar",
          "primaryKey": false,
          "notNull": false
        },
        "reference_id": {
          "name": "reference_id",
          "type": "varchar",
          "primaryKey": false,
          "notNull": false
        },
        "date": {
          "name": "date",
          "type": "timestamp",
          "primaryKey": false,
          "notNull": false
        },
        "memo": {
          "name": "memo",
          "type": "text",
          "primaryKey": false,
          "notNull": false
        },
        "data": {
          "name": "data",
          "type": "jsonb",
          "primaryKey": false,
          "notNull": false
        }
      },
      "indexes": {},
      "foreignKeys": {
        "ledger_ea_id_ledger_ea_id_fk": {
          "name": "ledger_ea_id_ledger_ea_id_fk",
          "tableFrom": "ledger",
          "tableTo": "ledger_ea",
          "columnsFrom": [
            "ea_id"
          ],
          "columnsTo": [
            "id"
          ],
          "onDelete": "cascade",
          "onUpdate": "no action"
        }
      },
      "compositePrimaryKeys": {},
      "uniqueConstraints": {
        "ledger_charge_plugin_charge_plugin_key_unique": {
          "name": "ledger_charge_plugin_charge_plugin_key_unique",
          "nullsNotDistinct": false,
          "columns": [
            "charge_plugin",
            "charge_plugin_key"
          ]
        }
      },
      "policies": {},
      "checkConstraints": {},
      "isRLSEnabled": false
    },
    "public.ledger_accounts": {
      "name": "ledger_accounts",
      "schema": "",
      "columns": {
        "id": {
          "name": "id",
          "type": "varchar",
          "primaryKey": true,
          "notNull": true,
          "default": "gen_random_uuid()"
        },
        "name": {
          "name": "name",
          "type": "text",
          "primaryKey": false,
          "notNull": true
        },
        "description": {
          "name": "description",
          "type": "text",
          "primaryKey": false,
          "notNull": false
        },
        "is_active": {
          "name": "is_active",
          "type": "boolean",
          "primaryKey": false,
          "notNull": true,
          "default": true
        },
        "data": {
          "name": "data",
          "type": "jsonb",
          "primaryKey": false,
          "notNull": false
        }
      },
      "indexes": {},
      "foreignKeys": {},
      "compositePrimaryKeys": {},
      "uniqueConstraints": {},
      "policies": {},
      "checkConstraints": {},
      "isRLSEnabled": false
    },
    "public.ledger_ea": {
      "name": "ledger_ea",
      "schema": "",
      "columns": {
        "id": {
          "name": "id",
          "type": "varchar",
          "primaryKey": true,
          "notNull": true,
          "default": "gen_random_uuid()"
        },
        "account_id": {
          "name": "account_id",
          "type": "varchar",
          "primaryKey": false,
          "notNull": true
        },
        "entity_type": {
          "name": "entity_type",
          "type": "varchar",
          "primaryKey": false,
          "notNull": true
        },
        "entity_id": {
          "name": "entity_id",
          "type": "varchar",
          "primaryKey": false,
          "notNull": true
        },
        "data": {
          "name": "data",
          "type": "jsonb",
          "primaryKey": false,
          "notNull": false
        }
      },
      "indexes": {},
      "foreignKeys": {
        "ledger_ea_account_id_ledger_accounts_id_fk": {
          "name": "ledger_ea_account_id_ledger_accounts_id_fk",
          "tableFrom": "ledger_ea",
          "tableTo": "ledger_accounts",
          "columnsFrom": [
            "account_id"
          ],
          "columnsTo": [
            "id"
          ],
          "onDelete": "no action",
          "onUpdate": "no action"
        }
      },
      "compositePrimaryKeys": {},
      "uniqueConstraints": {
        "ledger_ea_account_id_entity_id_unique": {
          "name": "ledger_ea_account_id_entity_id_unique",
          "nullsNotDistinct": false,
          "columns": [
            "account_id",
            "entity_id"
          ]
        }
      },
      "policies": {},
      "checkConstraints": {},
      "isRLSEnabled": false
    },
    "public.ledger_payments": {
      "name": "ledger_payments",
      "schema": "",
      "columns": {
        "id": {
          "name": "id",
          "type": "varchar",
          "primaryKey": true,
          "notNull": true,
          "default": "gen_random_uuid()"
        },
        "status": {
          "name": "status",
          "type": "text",
          "primaryKey": false,
          "notNull": true
        },
        "allocated": {
          "name": "allocated",
          "type": "boolean",
          "primaryKey": false,
          "notNull": true,
          "default": false
        },
        "amount": {
          "name": "amount",
          "type": "numeric(10, 2)",
          "primaryKey": false,
          "notNull": true
        },
        "payment_type": {
          "name": "payment_type",
          "type": "varchar",
          "primaryKey": false,
          "notNull": true
        },
        "ledger_ea_id": {
          "name": "ledger_ea_id",
          "type": "varchar",
          "primaryKey": false,
          "notNull": true
        },
        "details": {
          "name": "details",
          "type": "jsonb",
          "primaryKey": false,
          "notNull": false
        },
        "date_created": {
          "name": "date_created",
          "type": "timestamp",
          "primaryKey": false,
          "notNull": true,
          "default": "now()"
        },
        "date_received": {
          "name": "date_received",
          "type": "timestamp",
          "primaryKey": false,
          "notNull": false
        },
        "date_cleared": {
          "name": "date_cleared",
          "type": "timestamp",
          "primaryKey": false,
          "notNull": false
        },
        "memo": {
          "name": "memo",
          "type": "text",
          "primaryKey": false,
          "notNull": false
        }
      },
      "indexes": {},
      "foreignKeys": {
        "ledger_payments_payment_type_options_ledger_payment_type_id_fk": {
          "name": "ledger_payments_payment_type_options_ledger_payment_type_id_fk",
          "tableFrom": "ledger_payments",
          "tableTo": "options_ledger_payment_type",
          "columnsFrom": [
            "payment_type"
          ],
          "columnsTo": [
            "id"
          ],
          "onDelete": "no action",
          "onUpdate": "no action"
        },
        "ledger_payments_ledger_ea_id_ledger_ea_id_fk": {
          "name": "ledger_payments_ledger_ea_id_ledger_ea_id_fk",
          "tableFrom": "ledger_payments",
          "tableTo": "ledger_ea",
          "columnsFrom": [
            "ledger_ea_id"
          ],
          "columnsTo": [
            "id"
          ],
          "onDelete": "no action",
          "onUpdate": "no action"
        }
      },
      "compositePrimaryKeys": {},
      "uniqueConstraints": {},
      "policies": {},
      "checkConstraints": {},
      "isRLSEnabled": false
    },
    "public.ledger_stripe_paymentmethods": {
      "name": "ledger_stripe_paymentmethods",
      "schema": "",
      "columns": {
        "id": {
          "name": "id",
          "type": "varchar",
          "primaryKey": true,
          "notNull": true,
          "default": "gen_random_uuid()"
        },
        "entity_type": {
          "name": "entity_type",
          "type": "text",
          "primaryKey": false,
          "notNull": true
        },
        "entity_id": {
          "name": "entity_id",
          "type": "varchar",
          "primaryKey": false,
          "notNull": true
        },
        "payment_method": {
          "name": "payment_method",
          "type": "text",
          "primaryKey": false,
          "notNull": true
        },
        "is_active": {
          "name": "is_active",
          "type": "boolean",
          "primaryKey": false,
          "notNull": true,
          "default": true
        },
        "is_default": {
          "name": "is_default",
          "type": "boolean",
          "primaryKey": false,
          "notNull": true,
          "default": false
        },
        "created_at": {
          "name": "created_at",
          "type": "timestamp",
          "primaryKey": false,
          "notNull": true,
          "default": "now()"
        }
      },
      "indexes": {},
      "foreignKeys": {},
      "compositePrimaryKeys": {},
      "uniqueConstraints": {},
      "policies": {},
      "checkConstraints": {},
      "isRLSEnabled": false
    },
    "public.options_employer_contact_type": {
      "name": "options_employer_contact_type",
      "schema": "",
      "columns": {
        "id": {
          "name": "id",
          "type": "varchar",
          "primaryKey": true,
          "notNull": true,
          "default": "gen_random_uuid()"
        },
        "name": {
          "name": "name",
          "type": "text",
          "primaryKey": false,
          "notNull": true
        },
        "description": {
          "name": "description",
          "type": "text",
          "primaryKey": false,
          "notNull": false
        }
      },
      "indexes": {},
      "foreignKeys": {},
      "compositePrimaryKeys": {},
      "uniqueConstraints": {},
      "policies": {},
      "checkConstraints": {},
      "isRLSEnabled": false
    },
    "public.options_employment_status": {
      "name": "options_employment_status",
      "schema": "",
      "columns": {
        "id": {
          "name": "id",
          "type": "varchar",
          "primaryKey": true,
          "notNull": true,
          "default": "gen_random_uuid()"
        },
        "name": {
          "name": "name",
          "type": "text",
          "primaryKey": false,
          "notNull": true
        },
        "code": {
          "name": "code",
          "type": "varchar",
          "primaryKey": false,
          "notNull": true
        },
        "employed": {
          "name": "employed",
          "type": "boolean",
          "primaryKey": false,
          "notNull": true,
          "default": false
        },
        "description": {
          "name": "description",
          "type": "text",
          "primaryKey": false,
          "notNull": false
        },
        "sequence": {
          "name": "sequence",
          "type": "integer",
          "primaryKey": false,
          "notNull": true,
          "default": 0
        }
      },
      "indexes": {},
      "foreignKeys": {},
      "compositePrimaryKeys": {},
      "uniqueConstraints": {},
      "policies": {},
      "checkConstraints": {},
      "isRLSEnabled": false
    },
    "public.options_gender": {
      "name": "options_gender",
      "schema": "",
      "columns": {
        "id": {
          "name": "id",
          "type": "varchar",
          "primaryKey": true,
          "notNull": true,
          "default": "gen_random_uuid()"
        },
        "name": {
          "name": "name",
          "type": "text",
          "primaryKey": false,
          "notNull": true
        },
        "code": {
          "name": "code",
          "type": "varchar",
          "primaryKey": false,
          "notNull": true
        },
        "nota": {
          "name": "nota",
          "type": "boolean",
          "primaryKey": false,
          "notNull": true,
          "default": false
        },
        "sequence": {
          "name": "sequence",
          "type": "integer",
          "primaryKey": false,
          "notNull": true,
          "default": 0
        }
      },
      "indexes": {},
      "foreignKeys": {},
      "compositePrimaryKeys": {},
      "uniqueConstraints": {
        "options_gender_code_unique": {
          "name": "options_gender_code_unique",
          "nullsNotDistinct": false,
          "columns": [
            "code"
          ]
        }
      },
      "policies": {},
      "checkConstraints": {},
      "isRLSEnabled": false
    },
    "public.options_ledger_payment_type": {
      "name": "options_ledger_payment_type",
      "schema": "",
      "columns": {
        "id": {
          "name": "id",
          "type": "varchar",
          "primaryKey": true,
          "notNull": true,
          "default": "gen_random_uuid()"
        },
        "name": {
          "name": "name",
          "type": "text",
          "primaryKey": false,
          "notNull": true
        },
        "description": {
          "name": "description",
          "type": "text",
          "primaryKey": false,
          "notNull": false
        },
        "sequence": {
          "name": "sequence",
          "type": "integer",
          "primaryKey": false,
          "notNull": true,
          "default": 0
        }
      },
      "indexes": {},
      "foreignKeys": {},
      "compositePrimaryKeys": {},
      "uniqueConstraints": {},
      "policies": {},
      "checkConstraints": {},
      "isRLSEnabled": false
    },
    "public.options_trust_benefit_type": {
      "name": "options_trust_benefit_type",
      "schema": "",
      "columns": {
        "id": {
          "name": "id",
          "type": "varchar",
          "primaryKey": true,
          "notNull": true,
          "default": "gen_random_uuid()"
        },
        "name": {
          "name": "name",
          "type": "text",
          "primaryKey": false,
          "notNull": true
        },
        "icon": {
          "name": "icon",
          "type": "text",
          "primaryKey": false,
          "notNull": false
        },
        "sequence": {
          "name": "sequence",
          "type": "integer",
          "primaryKey": false,
          "notNull": true,
          "default": 0
        }
      },
      "indexes": {},
      "foreignKeys": {},
      "compositePrimaryKeys": {},
      "uniqueConstraints": {},
      "policies": {},
      "checkConstraints": {},
      "isRLSEnabled": false
    },
    "public.options_trust_provider_type": {
      "name": "options_trust_provider_type",
      "schema": "",
      "columns": {
        "id": {
          "name": "id",
          "type": "varchar",
          "primaryKey": true,
          "notNull": true,
          "default": "gen_random_uuid()"
        },
        "name": {
          "name": "name",
          "type": "text",
          "primaryKey": false,
          "notNull": true
        },
        "description": {
          "name": "description",
          "type": "text",
          "primaryKey": false,
          "notNull": false
        }
      },
      "indexes": {},
      "foreignKeys": {},
      "compositePrimaryKeys": {},
      "uniqueConstraints": {},
      "policies": {},
      "checkConstraints": {},
      "isRLSEnabled": false
    },
    "public.options_worker_id_type": {
      "name": "options_worker_id_type",
      "schema": "",
      "columns": {
        "id": {
          "name": "id",
          "type": "varchar",
          "primaryKey": true,
          "notNull": true,
          "default": "gen_random_uuid()"
        },
        "name": {
          "name": "name",
          "type": "text",
          "primaryKey": false,
          "notNull": true
        },
        "sequence": {
          "name": "sequence",
          "type": "integer",
          "primaryKey": false,
          "notNull": true,
          "default": 0
        },
        "validator": {
          "name": "validator",
          "type": "text",
          "primaryKey": false,
          "notNull": false
        }
      },
      "indexes": {},
      "foreignKeys": {},
      "compositePrimaryKeys": {},
      "uniqueConstraints": {},
      "policies": {},
      "checkConstraints": {},
      "isRLSEnabled": false
    },
    "public.options_worker_ws": {
      "name": "options_worker_ws",
      "schema": "",
      "columns": {
        "id": {
          "name": "id",
          "type": "varchar",
          "primaryKey": true,
          "notNull": true,
          "default": "gen_random_uuid()"
        },
        "name": {
          "name": "name",
          "type": "text",
          "primaryKey": false,
          "notNull": true
        },
        "description": {
          "name": "description",
          "type": "text",
          "primaryKey": false,
          "notNull": false
        },
        "sequence": {
          "name": "sequence",
          "type": "integer",
          "primaryKey": false,
          "notNull": true,
          "default": 0
        }
      },
      "indexes": {},
      "foreignKeys": {},
      "compositePrimaryKeys": {},
      "uniqueConstraints": {},
      "policies": {},
      "checkConstraints": {},
      "isRLSEnabled": false
    },
    "public.contact_phone": {
      "name": "contact_phone",
      "schema": "",
      "columns": {
        "id": {
          "name": "id",
          "type": "varchar",
          "primaryKey": true,
          "notNull": true,
          "default": "gen_random_uuid()"
        },
        "contact_id": {
          "name": "contact_id",
          "type": "varchar",
          "primaryKey": false,
          "notNull": true
        },
        "friendly_name": {
          "name": "friendly_name",
          "type": "text",
          "primaryKey": false,
          "notNull": false
        },
        "phone_number": {
          "name": "phone_number",
          "type": "text",
          "primaryKey": false,
          "notNull": true
        },
        "is_primary": {
          "name": "is_primary",
          "type": "boolean",
          "primaryKey": false,
          "notNull": true,
          "default": false
        },
        "is_active": {
          "name": "is_active",
          "type": "boolean",
          "primaryKey": false,
          "notNull": true,
          "default": true
        },
        "validation_response": {
          "name": "validation_response",
          "type": "jsonb",
          "primaryKey": false,
          "notNull": false
        },
        "created_at": {
          "name": "created_at",
          "type": "timestamp",
          "primaryKey": false,
          "notNull": true,
          "default": "now()"
        }
      },
      "indexes": {},
      "foreignKeys": {
        "contact_phone_contact_id_contacts_id_fk": {
          "name": "contact_phone_contact_id_contacts_id_fk",
          "tableFrom": "contact_phone",
          "tableTo": "contacts",
          "columnsFrom": [
            "contact_id"
          ],
          "columnsTo": [
            "id"
          ],
          "onDelete": "cascade",
          "onUpdate": "no action"
        }
      },
      "compositePrimaryKeys": {},
      "uniqueConstraints": {},
      "policies": {},
      "checkConstraints": {},
      "isRLSEnabled": false
    },
    "public.role_permissions": {
      "name": "role_permissions",
      "schema": "",
      "columns": {
        "role_id": {
          "name": "role_id",
          "type": "varchar",
          "primaryKey": false,
          "notNull": true
        },
        "permission_key": {
          "name": "permission_key",
          "type": "text",
          "primaryKey": false,
          "notNull": true
        },
        "assigned_at": {
          "name": "assigned_at",
          "type": "timestamp",
          "primaryKey": false,
          "notNull": true,
          "default": "now()"
        }
      },
      "indexes": {},
      "foreignKeys": {},
      "compositePrimaryKeys": {
        "role_permissions_role_id_permission_key_pk": {
          "name": "role_permissions_role_id_permission_key_pk",
          "columns": [
            "role_id",
            "permission_key"
          ]
        }
      },
      "uniqueConstraints": {},
      "policies": {},
      "checkConstraints": {},
      "isRLSEnabled": false
    },
    "public.roles": {
      "name": "roles",
      "schema": "",
      "columns": {
        "id": {
          "name": "id",
          "type": "varchar",
          "primaryKey": true,
          "notNull": true,
          "default": "gen_random_uuid()"
        },
        "name": {
          "name": "name",
          "type": "text",
          "primaryKey": false,
          "notNull": true
        },
        "description": {
          "name": "description",
          "type": "text",
          "primaryKey": false,
          "notNull": false
        },
        "sequence": {
          "name": "sequence",
          "type": "integer",
          "primaryKey": false,
          "notNull": true,
          "default": 0
        },
        "created_at": {
          "name": "created_at",
          "type": "timestamp",
          "primaryKey": false,
          "notNull": true,
          "default": "now()"
        }
      },
      "indexes": {},
      "foreignKeys": {},
      "compositePrimaryKeys": {},
      "uniqueConstraints": {
        "roles_name_unique": {
          "name": "roles_name_unique",
          "nullsNotDistinct": false,
          "columns": [
            "name"
          ]
        }
      },
      "policies": {},
      "checkConstraints": {},
      "isRLSEnabled": false
    },
    "public.sessions": {
      "name": "sessions",
      "schema": "",
      "columns": {
        "sid": {
          "name": "sid",
          "type": "varchar",
          "primaryKey": true,
          "notNull": true
        },
        "sess": {
          "name": "sess",
          "type": "jsonb",
          "primaryKey": false,
          "notNull": true
        },
        "expire": {
          "name": "expire",
          "type": "timestamp",
          "primaryKey": false,
          "notNull": true
        }
      },
      "indexes": {
        "IDX_session_expire": {
          "name": "IDX_session_expire",
          "columns": [
            {
              "expression": "expire",
              "isExpression": false,
              "asc": true,
              "nulls": "last"
            }
          ],
          "isUnique": false,
          "concurrently": false,
          "method": "btree",
          "with": {}
        }
      },
      "foreignKeys": {},
      "compositePrimaryKeys": {},
      "uniqueConstraints": {},
      "policies": {},
      "checkConstraints": {},
      "isRLSEnabled": false
    },
    "public.trust_benefits": {
      "name": "trust_benefits",
      "schema": "",
      "columns": {
        "id": {
          "name": "id",
          "type": "varchar",
          "primaryKey": true,
          "notNull": true,
          "default": "gen_random_uuid()"
        },
        "name": {
          "name": "name",
          "type": "text",
          "primaryKey": false,
          "notNull": true
        },
        "benefit_type": {
          "name": "benefit_type",
          "type": "varchar",
          "primaryKey": false,
          "notNull": false
        },
        "is_active": {
          "name": "is_active",
          "type": "boolean",
          "primaryKey": false,
          "notNull": true,
          "default": true
        },
        "description": {
          "name": "description",
          "type": "text",
          "primaryKey": false,
          "notNull": false
        }
      },
      "indexes": {},
      "foreignKeys": {
        "trust_benefits_benefit_type_options_trust_benefit_type_id_fk": {
          "name": "trust_benefits_benefit_type_options_trust_benefit_type_id_fk",
          "tableFrom": "trust_benefits",
          "tableTo": "options_trust_benefit_type",
          "columnsFrom": [
            "benefit_type"
          ],
          "columnsTo": [
            "id"
          ],
          "onDelete": "set null",
          "onUpdate": "no action"
        }
      },
      "compositePrimaryKeys": {},
      "uniqueConstraints": {},
      "policies": {},
      "checkConstraints": {},
      "isRLSEnabled": false
    },
    "public.trust_provider_contacts": {
      "name": "trust_provider_contacts",
      "schema": "",
      "columns": {
        "id": {
          "name": "id",
          "type": "varchar",
          "primaryKey": true,
          "notNull": true,
          "default": "gen_random_uuid()"
        },
        "provider_id": {
          "name": "provider_id",
          "type": "varchar",
          "primaryKey": false,
          "notNull": true
        },
        "contact_id": {
          "name": "contact_id",
          "type": "varchar",
          "primaryKey": false,
          "notNull": true
        },
        "contact_type_id": {
          "name": "contact_type_id",
          "type": "varchar",
          "primaryKey": false,
          "notNull": false
        }
      },
      "indexes": {},
      "foreignKeys": {
        "trust_provider_contacts_provider_id_trust_providers_id_fk": {
          "name": "trust_provider_contacts_provider_id_trust_providers_id_fk",
          "tableFrom": "trust_provider_contacts",
          "tableTo": "trust_providers",
          "columnsFrom": [
            "provider_id"
          ],
          "columnsTo": [
            "id"
          ],
          "onDelete": "cascade",
          "onUpdate": "no action"
        },
        "trust_provider_contacts_contact_id_contacts_id_fk": {
          "name": "trust_provider_contacts_contact_id_contacts_id_fk",
          "tableFrom": "trust_provider_contacts",
          "tableTo": "contacts",
          "columnsFrom": [
            "contact_id"
          ],
          "columnsTo": [
            "id"
          ],
          "onDelete": "cascade",
          "onUpdate": "no action"
        },
        "trust_provider_contacts_contact_type_id_options_trust_provider_type_id_fk": {
          "name": "trust_provider_contacts_contact_type_id_options_trust_provider_type_id_fk",
          "tableFrom": "trust_provider_contacts",
          "tableTo": "options_trust_provider_type",
          "columnsFrom": [
            "contact_type_id"
          ],
          "columnsTo": [
            "id"
          ],
          "onDelete": "set null",
          "onUpdate": "no action"
        }
      },
      "compositePrimaryKeys": {},
      "uniqueConstraints": {},
      "policies": {},
      "checkConstraints": {},
      "isRLSEnabled": false
    },
    "public.trust_providers": {
      "name": "trust_providers",
      "schema": "",
      "columns": {
        "id": {
          "name": "id",
          "type": "varchar",
          "primaryKey": true,
          "notNull": true,
          "default": "gen_random_uuid()"
        },
        "name": {
          "name": "name",
          "type": "text",
          "primaryKey": false,
          "notNull": true
        },
        "data": {
          "name": "data",
          "type": "jsonb",
          "primaryKey": false,
          "notNull": false
        }
      },
      "indexes": {},
      "foreignKeys": {},
      "compositePrimaryKeys": {},
      "uniqueConstraints": {},
      "policies": {},
      "checkConstraints": {},
      "isRLSEnabled": false
    },
    "public.trust_wmb": {
      "name": "trust_wmb",
      "schema": "",
      "columns": {
        "id": {
          "name": "id",
          "type": "varchar",
          "primaryKey": true,
          "notNull": true,
          "default": "gen_random_uuid()"
        },
        "month": {
          "name": "month",
          "type": "integer",
          "primaryKey": false,
          "notNull": true
        },
        "year": {
          "name": "year",
          "type": "integer",
          "primaryKey": false,
          "notNull": true
        },
        "worker_id": {
          "name": "worker_id",
          "type": "varchar",
          "primaryKey": false,
          "notNull": true
        },
        "employer_id": {
          "name": "employer_id",
          "type": "varchar",
          "primaryKey": false,
          "notNull": true
        },
        "benefit_id": {
          "name": "benefit_id",
          "type": "varchar",
          "primaryKey": false,
          "notNull": true
        }
      },
      "indexes": {},
      "foreignKeys": {
        "trust_wmb_worker_id_workers_id_fk": {
          "name": "trust_wmb_worker_id_workers_id_fk",
          "tableFrom": "trust_wmb",
          "tableTo": "workers",
          "columnsFrom": [
            "worker_id"
          ],
          "columnsTo": [
            "id"
          ],
          "onDelete": "cascade",
          "onUpdate": "no action"
        },
        "trust_wmb_employer_id_employers_id_fk": {
          "name": "trust_wmb_employer_id_employers_id_fk",
          "tableFrom": "trust_wmb",
          "tableTo": "employers",
          "columnsFrom": [
            "employer_id"
          ],
          "columnsTo": [
            "id"
          ],
          "onDelete": "cascade",
          "onUpdate": "no action"
        },
        "trust_wmb_benefit_id_trust_benefits_id_fk": {
          "name": "trust_wmb_benefit_id_trust_benefits_id_fk",
          "tableFrom": "trust_wmb",
          "tableTo": "trust_benefits",
          "columnsFrom": [
            "benefit_id"
          ],
          "columnsTo": [
            "id"
          ],
          "onDelete": "cascade",
          "onUpdate": "no action"
        }
      },
      "compositePrimaryKeys": {},
      "uniqueConstraints": {
        "trust_wmb_worker_id_employer_id_benefit_id_month_year_unique": {
          "name": "trust_wmb_worker_id_employer_id_benefit_id_month_year_unique",
          "nullsNotDistinct": false,
          "columns": [
            "worker_id",
            "employer_id",
            "benefit_id",
            "month",
            "year"
          ]
        }
      },
      "policies": {},
      "checkConstraints": {},
      "isRLSEnabled": false
    },
    "public.user_roles": {
      "name": "user_roles",
      "schema": "",
      "columns": {
        "user_id": {
          "name": "user_id",
          "type": "varchar",
          "primaryKey": false,
          "notNull": true
        },
        "role_id": {
          "name": "role_id",
          "type": "varchar",
          "primaryKey": false,
          "notNull": true
        },
        "assigned_at": {
          "name": "assigned_at",
          "type": "timestamp",
          "primaryKey": false,
          "notNull": true,
          "default": "now()"
        }
      },
      "indexes": {},
      "foreignKeys": {},
      "compositePrimaryKeys": {
        "user_roles_user_id_role_id_pk": {
          "name": "user_roles_user_id_role_id_pk",
          "columns": [
            "user_id",
            "role_id"
          ]
        }
      },
      "uniqueConstraints": {},
      "policies": {},
      "checkConstraints": {},
      "isRLSEnabled": false
    },
    "public.users": {
      "name": "users",
      "schema": "",
      "columns": {
        "id": {
          "name": "id",
          "type": "varchar",
          "primaryKey": true,
          "notNull": true,
          "default": "gen_random_uuid()"
        },
        "replit_user_id": {
          "name": "replit_user_id",
          "type": "varchar",
          "primaryKey": false,
          "notNull": false
        },
        "email": {
          "name": "email",
          "type": "varchar",
          "primaryKey": false,
          "notNull": true
        },
        "first_name": {
          "name": "first_name",
          "type": "varchar",
          "primaryKey": false,
          "notNull": false
        },
        "last_name": {
          "name": "last_name",
          "type": "varchar",
          "primaryKey": false,
          "notNull": false
        },
        "profile_image_url": {
          "name": "profile_image_url",
          "type": "varchar",
          "primaryKey": false,
          "notNull": false
        },
        "account_status": {
          "name": "account_status",
          "type": "varchar",
          "primaryKey": false,
          "notNull": true,
          "default": "'pending'"
        },
        "is_active": {
          "name": "is_active",
          "type": "boolean",
          "primaryKey": false,
          "notNull": true,
          "default": true
        },
        "created_at": {
          "name": "created_at",
          "type": "timestamp",
          "primaryKey": false,
          "notNull": true,
          "default": "now()"
        },
        "updated_at": {
          "name": "updated_at",
          "type": "timestamp",
          "primaryKey": false,
          "notNull": true,
          "default": "now()"
        },
        "last_login": {
          "name": "last_login",
          "type": "timestamp",
          "primaryKey": false,
          "notNull": false
        }
      },
      "indexes": {},
      "foreignKeys": {},
      "compositePrimaryKeys": {},
      "uniqueConstraints": {
        "users_replit_user_id_unique": {
          "name": "users_replit_user_id_unique",
          "nullsNotDistinct": false,
          "columns": [
            "replit_user_id"
          ]
        },
        "users_email_unique": {
          "name": "users_email_unique",
          "nullsNotDistinct": false,
          "columns": [
            "email"
          ]
        }
      },
      "policies": {},
      "checkConstraints": {},
      "isRLSEnabled": false
    },
    "public.variables": {
      "name": "variables",
      "schema": "",
      "columns": {
        "id": {
          "name": "id",
          "type": "varchar",
          "primaryKey": true,
          "notNull": true,
          "default": "gen_random_uuid()"
        },
        "name": {
          "name": "name",
          "type": "text",
          "primaryKey": false,
          "notNull": true
        },
        "value": {
          "name": "value",
          "type": "jsonb",
          "primaryKey": false,
          "notNull": true
        }
      },
      "indexes": {},
      "foreignKeys": {},
      "compositePrimaryKeys": {},
      "uniqueConstraints": {
        "variables_name_unique": {
          "name": "variables_name_unique",
          "nullsNotDistinct": false,
          "columns": [
            "name"
          ]
        }
      },
      "policies": {},
      "checkConstraints": {},
      "isRLSEnabled": false
    },
    "public.winston_logs": {
      "name": "winston_logs",
      "schema": "",
      "columns": {
        "id": {
          "name": "id",
          "type": "serial",
          "primaryKey": true,
          "notNull": true
        },
        "level": {
          "name": "level",
          "type": "varchar(20)",
          "primaryKey": false,
          "notNull": false
        },
        "message": {
          "name": "message",
          "type": "text",
          "primaryKey": false,
          "notNull": false
        },
        "timestamp": {
          "name": "timestamp",
          "type": "timestamp",
          "primaryKey": false,
          "notNull": false,
          "default": "now()"
        },
        "source": {
          "name": "source",
          "type": "varchar(50)",
          "primaryKey": false,
          "notNull": false
        },
        "meta": {
          "name": "meta",
          "type": "jsonb",
          "primaryKey": false,
          "notNull": false
        },
        "module": {
          "name": "module",
          "type": "varchar(100)",
          "primaryKey": false,
          "notNull": false
        },
        "operation": {
          "name": "operation",
          "type": "varchar(100)",
          "primaryKey": false,
          "notNull": false
        },
        "entity_id": {
          "name": "entity_id",
          "type": "varchar(255)",
          "primaryKey": false,
          "notNull": false
        },
        "host_entity_id": {
          "name": "host_entity_id",
          "type": "varchar(255)",
          "primaryKey": false,
          "notNull": false
        },
        "description": {
          "name": "description",
          "type": "text",
          "primaryKey": false,
          "notNull": false
        },
        "user_id": {
          "name": "user_id",
          "type": "varchar(255)",
          "primaryKey": false,
          "notNull": false
        },
        "user_email": {
          "name": "user_email",
          "type": "varchar(255)",
          "primaryKey": false,
          "notNull": false
        },
        "ip_address": {
          "name": "ip_address",
          "type": "varchar(45)",
          "primaryKey": false,
          "notNull": false
        }
      },
      "indexes": {
        "idx_winston_logs_entity_id": {
          "name": "idx_winston_logs_entity_id",
          "columns": [
            {
              "expression": "entity_id",
              "isExpression": false,
              "asc": true,
              "nulls": "last"
            }
          ],
          "isUnique": false,
          "concurrently": false,
          "method": "btree",
          "with": {}
        },
        "idx_winston_logs_host_entity_id": {
          "name": "idx_winston_logs_host_entity_id",
          "columns": [
            {
              "expression": "host_entity_id",
              "isExpression": false,
              "asc": true,
              "nulls": "last"
            }
          ],
          "isUnique": false,
          "concurrently": false,
          "method": "btree",
          "with": {}
        },
        "idx_winston_logs_module": {
          "name": "idx_winston_logs_module",
          "columns": [
            {
              "expression": "module",
              "isExpression": false,
              "asc": true,
              "nulls": "last"
            }
          ],
          "isUnique": false,
          "concurrently": false,
          "method": "btree",
          "with": {}
        },
        "idx_winston_logs_operation": {
          "name": "idx_winston_logs_operation",
          "columns": [
            {
              "expression": "operation",
              "isExpression": false,
              "asc": true,
              "nulls": "last"
            }
          ],
          "isUnique": false,
          "concurrently": false,
          "method": "btree",
          "with": {}
        },
        "idx_winston_logs_user_id": {
          "name": "idx_winston_logs_user_id",
          "columns": [
            {
              "expression": "user_id",
              "isExpression": false,
              "asc": true,
              "nulls": "last"
            }
          ],
          "isUnique": false,
          "concurrently": false,
          "method": "btree",
          "with": {}
        }
      },
      "foreignKeys": {},
      "compositePrimaryKeys": {},
      "uniqueConstraints": {},
      "policies": {},
      "checkConstraints": {},
      "isRLSEnabled": false
    },
    "public.wizard_employer_monthly": {
      "name": "wizard_employer_monthly",
      "schema": "",
      "columns": {
        "wizard_id": {
          "name": "wizard_id",
          "type": "varchar",
          "primaryKey": true,
          "notNull": true
        },
        "employer_id": {
          "name": "employer_id",
          "type": "varchar",
          "primaryKey": false,
          "notNull": true
        },
        "year": {
          "name": "year",
          "type": "integer",
          "primaryKey": false,
          "notNull": true
        },
        "month": {
          "name": "month",
          "type": "integer",
          "primaryKey": false,
          "notNull": true
        }
      },
      "indexes": {
        "idx_wizard_employer_monthly_period": {
          "name": "idx_wizard_employer_monthly_period",
          "columns": [
            {
              "expression": "year",
              "isExpression": false,
              "asc": true,
              "nulls": "last"
            },
            {
              "expression": "month",
              "isExpression": false,
              "asc": true,
              "nulls": "last"
            }
          ],
          "isUnique": false,
          "concurrently": false,
          "method": "btree",
          "with": {}
        },
        "idx_wizard_employer_monthly_employer": {
          "name": "idx_wizard_employer_monthly_employer",
          "columns": [
            {
              "expression": "employer_id",
              "isExpression": false,
              "asc": true,
              "nulls": "last"
            }
          ],
          "isUnique": false,
          "concurrently": false,
          "method": "btree",
          "with": {}
        }
      },
      "foreignKeys": {
        "wizard_employer_monthly_wizard_id_wizards_id_fk": {
          "name": "wizard_employer_monthly_wizard_id_wizards_id_fk",
          "tableFrom": "wizard_employer_monthly",
          "tableTo": "wizards",
          "columnsFrom": [
            "wizard_id"
          ],
          "columnsTo": [
            "id"
          ],
          "onDelete": "cascade",
          "onUpdate": "no action"
        },
        "wizard_employer_monthly_employer_id_employers_id_fk": {
          "name": "wizard_employer_monthly_employer_id_employers_id_fk",
          "tableFrom": "wizard_employer_monthly",
          "tableTo": "employers",
          "columnsFrom": [
            "employer_id"
          ],
          "columnsTo": [
            "id"
          ],
          "onDelete": "cascade",
          "onUpdate": "no action"
        }
      },
      "compositePrimaryKeys": {},
      "uniqueConstraints": {},
      "policies": {},
      "checkConstraints": {},
      "isRLSEnabled": false
    },
    "public.wizard_feed_mappings": {
      "name": "wizard_feed_mappings",
      "schema": "",
      "columns": {
        "id": {
          "name": "id",
          "type": "varchar",
          "primaryKey": true,
          "notNull": true,
          "default": "gen_random_uuid()"
        },
        "user_id": {
          "name": "user_id",
          "type": "varchar",
          "primaryKey": false,
          "notNull": true
        },
        "type": {
          "name": "type",
          "type": "varchar",
          "primaryKey": false,
          "notNull": true
        },
        "first_row_hash": {
          "name": "first_row_hash",
          "type": "varchar",
          "primaryKey": false,
          "notNull": true
        },
        "mapping": {
          "name": "mapping",
          "type": "jsonb",
          "primaryKey": false,
          "notNull": true
        },
        "created_at": {
          "name": "created_at",
          "type": "timestamp",
          "primaryKey": false,
          "notNull": true,
          "default": "now()"
        },
        "updated_at": {
          "name": "updated_at",
          "type": "timestamp",
          "primaryKey": false,
          "notNull": true,
          "default": "now()"
        }
      },
      "indexes": {
        "idx_wizard_feed_mappings_user_type_hash": {
          "name": "idx_wizard_feed_mappings_user_type_hash",
          "columns": [
            {
              "expression": "user_id",
              "isExpression": false,
              "asc": true,
              "nulls": "last"
            },
            {
              "expression": "type",
              "isExpression": false,
              "asc": true,
              "nulls": "last"
            },
            {
              "expression": "first_row_hash",
              "isExpression": false,
              "asc": true,
              "nulls": "last"
            }
          ],
          "isUnique": false,
          "concurrently": false,
          "method": "btree",
          "with": {}
        }
      },
      "foreignKeys": {
        "wizard_feed_mappings_user_id_users_id_fk": {
          "name": "wizard_feed_mappings_user_id_users_id_fk",
          "tableFrom": "wizard_feed_mappings",
          "tableTo": "users",
          "columnsFrom": [
            "user_id"
          ],
          "columnsTo": [
            "id"
          ],
          "onDelete": "cascade",
          "onUpdate": "no action"
        }
      },
      "compositePrimaryKeys": {},
      "uniqueConstraints": {},
      "policies": {},
      "checkConstraints": {},
      "isRLSEnabled": false
    },
    "public.wizard_report_data": {
      "name": "wizard_report_data",
      "schema": "",
      "columns": {
        "id": {
          "name": "id",
          "type": "varchar",
          "primaryKey": true,
          "notNull": true,
          "default": "gen_random_uuid()"
        },
        "wizard_id": {
          "name": "wizard_id",
          "type": "varchar",
          "primaryKey": false,
          "notNull": true
        },
        "pk": {
          "name": "pk",
          "type": "varchar",
          "primaryKey": false,
          "notNull": true
        },
        "data": {
          "name": "data",
          "type": "jsonb",
          "primaryKey": false,
          "notNull": false
        },
        "created_at": {
          "name": "created_at",
          "type": "timestamp",
          "primaryKey": false,
          "notNull": true,
          "default": "now()"
        }
      },
      "indexes": {
        "idx_wizard_report_data_wizard_id": {
          "name": "idx_wizard_report_data_wizard_id",
          "columns": [
            {
              "expression": "wizard_id",
              "isExpression": false,
              "asc": true,
              "nulls": "last"
            }
          ],
          "isUnique": false,
          "concurrently": false,
          "method": "btree",
          "with": {}
        }
      },
      "foreignKeys": {
        "wizard_report_data_wizard_id_wizards_id_fk": {
          "name": "wizard_report_data_wizard_id_wizards_id_fk",
          "tableFrom": "wizard_report_data",
          "tableTo": "wizards",
          "columnsFrom": [
            "wizard_id"
          ],
          "columnsTo": [
            "id"
          ],
          "onDelete": "cascade",
          "onUpdate": "no action"
        }
      },
      "compositePrimaryKeys": {},
      "uniqueConstraints": {
        "idx_wizard_report_data_wizard_id_pk": {
          "name": "idx_wizard_report_data_wizard_id_pk",
          "nullsNotDistinct": false,
          "columns": [
            "wizard_id",
            "pk"
          ]
        }
      },
      "policies": {},
      "checkConstraints": {},
      "isRLSEnabled": false
    },
    "public.wizards": {
      "name": "wizards",
      "schema": "",
      "columns": {
        "id": {
          "name": "id",
          "type": "varchar",
          "primaryKey": true,
          "notNull": true,
          "default": "gen_random_uuid()"
        },
        "date": {
          "name": "date",
          "type": "timestamp",
          "primaryKey": false,
          "notNull": true,
          "default": "now()"
        },
        "type": {
          "name": "type",
          "type": "varchar",
          "primaryKey": false,
          "notNull": true
        },
        "status": {
          "name": "status",
          "type": "varchar",
          "primaryKey": false,
          "notNull": true
        },
        "current_step": {
          "name": "current_step",
          "type": "varchar",
          "primaryKey": false,
          "notNull": false
        },
        "entity_id": {
          "name": "entity_id",
          "type": "varchar",
          "primaryKey": false,
          "notNull": false
        },
        "data": {
          "name": "data",
          "type": "jsonb",
          "primaryKey": false,
          "notNull": false
        }
      },
      "indexes": {},
      "foreignKeys": {},
      "compositePrimaryKeys": {},
      "uniqueConstraints": {},
      "policies": {},
      "checkConstraints": {},
      "isRLSEnabled": false
    },
    "public.worker_hours": {
      "name": "worker_hours",
      "schema": "",
      "columns": {
        "id": {
          "name": "id",
          "type": "varchar",
          "primaryKey": true,
          "notNull": true,
          "default": "gen_random_uuid()"
        },
        "year": {
          "name": "year",
          "type": "integer",
          "primaryKey": false,
          "notNull": true
        },
        "month": {
          "name": "month",
          "type": "integer",
          "primaryKey": false,
          "notNull": true
        },
        "day": {
          "name": "day",
          "type": "integer",
          "primaryKey": false,
          "notNull": true
        },
        "worker_id": {
          "name": "worker_id",
          "type": "varchar",
          "primaryKey": false,
          "notNull": true
        },
        "employer_id": {
          "name": "employer_id",
          "type": "varchar",
          "primaryKey": false,
          "notNull": true
        },
        "employment_status_id": {
          "name": "employment_status_id",
          "type": "varchar",
          "primaryKey": false,
          "notNull": true
        },
        "hours": {
          "name": "hours",
          "type": "double precision",
          "primaryKey": false,
          "notNull": false
        },
        "home": {
          "name": "home",
          "type": "boolean",
          "primaryKey": false,
          "notNull": true,
          "default": false
        }
      },
      "indexes": {},
      "foreignKeys": {
        "worker_hours_worker_id_workers_id_fk": {
          "name": "worker_hours_worker_id_workers_id_fk",
          "tableFrom": "worker_hours",
          "tableTo": "workers",
          "columnsFrom": [
            "worker_id"
          ],
          "columnsTo": [
            "id"
          ],
          "onDelete": "cascade",
          "onUpdate": "no action"
        },
        "worker_hours_employer_id_employers_id_fk": {
          "name": "worker_hours_employer_id_employers_id_fk",
          "tableFrom": "worker_hours",
          "tableTo": "employers",
          "columnsFrom": [
            "employer_id"
          ],
          "columnsTo": [
            "id"
          ],
          "onDelete": "cascade",
          "onUpdate": "no action"
        },
        "worker_hours_employment_status_id_options_employment_status_id_fk": {
          "name": "worker_hours_employment_status_id_options_employment_status_id_fk",
          "tableFrom": "worker_hours",
          "tableTo": "options_employment_status",
          "columnsFrom": [
            "employment_status_id"
          ],
          "columnsTo": [
            "id"
          ],
          "onDelete": "cascade",
          "onUpdate": "no action"
        }
      },
      "compositePrimaryKeys": {},
      "uniqueConstraints": {
        "worker_hours_worker_id_employer_id_year_month_day_unique": {
          "name": "worker_hours_worker_id_employer_id_year_month_day_unique",
          "nullsNotDistinct": false,
          "columns": [
            "worker_id",
            "employer_id",
            "year",
            "month",
            "day"
          ]
        }
      },
      "policies": {},
      "checkConstraints": {},
      "isRLSEnabled": false
    },
    "public.worker_ids": {
      "name": "worker_ids",
      "schema": "",
      "columns": {
        "id": {
          "name": "id",
          "type": "varchar",
          "primaryKey": true,
          "notNull": true,
          "default": "gen_random_uuid()"
        },
        "worker_id": {
          "name": "worker_id",
          "type": "varchar",
          "primaryKey": false,
          "notNull": true
        },
        "type_id": {
          "name": "type_id",
          "type": "varchar",
          "primaryKey": false,
          "notNull": true
        },
        "value": {
          "name": "value",
          "type": "text",
          "primaryKey": false,
          "notNull": true
        }
      },
      "indexes": {},
      "foreignKeys": {
        "worker_ids_worker_id_workers_id_fk": {
          "name": "worker_ids_worker_id_workers_id_fk",
          "tableFrom": "worker_ids",
          "tableTo": "workers",
          "columnsFrom": [
            "worker_id"
          ],
          "columnsTo": [
            "id"
          ],
          "onDelete": "cascade",
          "onUpdate": "no action"
        },
        "worker_ids_type_id_options_worker_id_type_id_fk": {
          "name": "worker_ids_type_id_options_worker_id_type_id_fk",
          "tableFrom": "worker_ids",
          "tableTo": "options_worker_id_type",
          "columnsFrom": [
            "type_id"
          ],
          "columnsTo": [
            "id"
          ],
          "onDelete": "cascade",
          "onUpdate": "no action"
        }
      },
      "compositePrimaryKeys": {},
      "uniqueConstraints": {
        "worker_ids_type_id_value_unique": {
          "name": "worker_ids_type_id_value_unique",
          "nullsNotDistinct": false,
          "columns": [
            "type_id",
            "value"
          ]
        }
      },
      "policies": {},
      "checkConstraints": {},
      "isRLSEnabled": false
    },
    "public.worker_wsh": {
      "name": "worker_wsh",
      "schema": "",
      "columns": {
        "id": {
          "name": "id",
          "type": "varchar",
          "primaryKey": true,
          "notNull": true,
          "default": "gen_random_uuid()"
        },
        "date": {
          "name": "date",
          "type": "date",
          "primaryKey": false,
          "notNull": true
        },
        "worker_id": {
          "name": "worker_id",
          "type": "varchar",
          "primaryKey": false,
          "notNull": true
        },
        "ws_id": {
          "name": "ws_id",
          "type": "varchar",
          "primaryKey": false,
          "notNull": true
        },
        "data": {
          "name": "data",
          "type": "jsonb",
          "primaryKey": false,
          "notNull": false
        },
        "created_at": {
          "name": "created_at",
          "type": "timestamp",
          "primaryKey": false,
          "notNull": true,
          "default": "now()"
        }
      },
      "indexes": {},
      "foreignKeys": {
        "worker_wsh_worker_id_workers_id_fk": {
          "name": "worker_wsh_worker_id_workers_id_fk",
          "tableFrom": "worker_wsh",
          "tableTo": "workers",
          "columnsFrom": [
            "worker_id"
          ],
          "columnsTo": [
            "id"
          ],
          "onDelete": "cascade",
          "onUpdate": "no action"
        },
        "worker_wsh_ws_id_options_worker_ws_id_fk": {
          "name": "worker_wsh_ws_id_options_worker_ws_id_fk",
          "tableFrom": "worker_wsh",
          "tableTo": "options_worker_ws",
          "columnsFrom": [
            "ws_id"
          ],
          "columnsTo": [
            "id"
          ],
          "onDelete": "cascade",
          "onUpdate": "no action"
        }
      },
      "compositePrimaryKeys": {},
      "uniqueConstraints": {},
      "policies": {},
      "checkConstraints": {},
      "isRLSEnabled": false
    },
    "public.workers": {
      "name": "workers",
      "schema": "",
      "columns": {
        "id": {
          "name": "id",
          "type": "varchar",
          "primaryKey": true,
          "notNull": true,
          "default": "gen_random_uuid()"
        },
        "sirius_id": {
          "name": "sirius_id",
          "type": "serial",
          "primaryKey": false,
          "notNull": true
        },
        "contact_id": {
          "name": "contact_id",
          "type": "varchar",
          "primaryKey": false,
          "notNull": true
        },
        "ssn": {
          "name": "ssn",
          "type": "text",
          "primaryKey": false,
          "notNull": false
        },
        "denorm_ws_id": {
          "name": "denorm_ws_id",
          "type": "varchar",
          "primaryKey": false,
          "notNull": false
        },
        "denorm_home_employer_id": {
          "name": "denorm_home_employer_id",
          "type": "varchar",
          "primaryKey": false,
          "notNull": false
        },
        "denorm_employer_ids": {
          "name": "denorm_employer_ids",
          "type": "varchar[]",
          "primaryKey": false,
          "notNull": false
        }
      },
      "indexes": {},
      "foreignKeys": {
        "workers_contact_id_contacts_id_fk": {
          "name": "workers_contact_id_contacts_id_fk",
          "tableFrom": "workers",
          "tableTo": "contacts",
          "columnsFrom": [
            "contact_id"
          ],
          "columnsTo": [
            "id"
          ],
          "onDelete": "cascade",
          "onUpdate": "no action"
        },
        "workers_denorm_ws_id_options_worker_ws_id_fk": {
          "name": "workers_denorm_ws_id_options_worker_ws_id_fk",
          "tableFrom": "workers",
          "tableTo": "options_worker_ws",
          "columnsFrom": [
            "denorm_ws_id"
          ],
          "columnsTo": [
            "id"
          ],
          "onDelete": "set null",
          "onUpdate": "no action"
        },
        "workers_denorm_home_employer_id_employers_id_fk": {
          "name": "workers_denorm_home_employer_id_employers_id_fk",
          "tableFrom": "workers",
          "tableTo": "employers",
          "columnsFrom": [
            "denorm_home_employer_id"
          ],
          "columnsTo": [
            "id"
          ],
          "onDelete": "set null",
          "onUpdate": "no action"
        }
      },
      "compositePrimaryKeys": {},
      "uniqueConstraints": {
        "workers_sirius_id_unique": {
          "name": "workers_sirius_id_unique",
          "nullsNotDistinct": false,
          "columns": [
            "sirius_id"
          ]
        },
        "workers_ssn_unique": {
          "name": "workers_ssn_unique",
          "nullsNotDistinct": false,
          "columns": [
            "ssn"
          ]
        }
      },
      "policies": {},
      "checkConstraints": {},
      "isRLSEnabled": false
    }
  },
  "enums": {},
  "schemas": {},
  "sequences": {},
  "roles": {},
  "policies": {},
  "views": {},
  "_meta": {
    "columns": {},
    "schemas": {},
    "tables": {}
  }
}